RustChengxushejiYuyanFix1/README.md
RustChengxushejiYuyanFix1/__init__.py
RustChengxushejiYuyanFix1/__main__.py
RustChengxushejiYuyanFix1/file.epub
RustChengxushejiYuyanFix1/index.html
RustChengxushejiYuyanFix1/css/__init__.py
RustChengxushejiYuyanFix1/css/annotations.css
RustChengxushejiYuyanFix1/css/main.css
RustChengxushejiYuyanFix1/css/normalize.css
RustChengxushejiYuyanFix1/css/popup.css
RustChengxushejiYuyanFix1/font/__init__.py
RustChengxushejiYuyanFix1/font/fontello.eot
RustChengxushejiYuyanFix1/font/fontello.svg
RustChengxushejiYuyanFix1/font/fontello.ttf
RustChengxushejiYuyanFix1/font/fontello.woff
RustChengxushejiYuyanFix1/img/__init__.py
RustChengxushejiYuyanFix1/img/annotator-glyph-sprite.png
RustChengxushejiYuyanFix1/img/annotator-icon-sprite.png
RustChengxushejiYuyanFix1/img/apple-touch-icon.png
RustChengxushejiYuyanFix1/img/cancelfullscreen.png
RustChengxushejiYuyanFix1/img/close.png
RustChengxushejiYuyanFix1/img/fullscreen.png
RustChengxushejiYuyanFix1/img/loader.gif
RustChengxushejiYuyanFix1/img/menu-icon.png
RustChengxushejiYuyanFix1/img/save.png
RustChengxushejiYuyanFix1/img/saved.png
RustChengxushejiYuyanFix1/img/settings-s.png
RustChengxushejiYuyanFix1/img/settings.png
RustChengxushejiYuyanFix1/img/star.png
RustChengxushejiYuyanFix1/js/__init__.py
RustChengxushejiYuyanFix1/js/epub.js
RustChengxushejiYuyanFix1/js/epub.min.js
RustChengxushejiYuyanFix1/js/epub.min.map
RustChengxushejiYuyanFix1/js/hooks.min.js
RustChengxushejiYuyanFix1/js/hooks.min.map
RustChengxushejiYuyanFix1/js/reader.js
RustChengxushejiYuyanFix1/js/reader.js.map
RustChengxushejiYuyanFix1/js/reader.min.js
RustChengxushejiYuyanFix1/js/reader.min.map
RustChengxushejiYuyanFix1/js/hooks/__init__.py
RustChengxushejiYuyanFix1/js/hooks/extensions/__init__.py
RustChengxushejiYuyanFix1/js/hooks/extensions/highlight.js
RustChengxushejiYuyanFix1/js/libs/__init__.py
RustChengxushejiYuyanFix1/js/libs/jquery.min.js
RustChengxushejiYuyanFix1/js/libs/localforage.min.js
rust_chengxusheji_yuyan_fix1-2025.3.25.1.dist-info/METADATA
rust_chengxusheji_yuyan_fix1-2025.3.25.1.dist-info/WHEEL
rust_chengxusheji_yuyan_fix1-2025.3.25.1.dist-info/entry_points.txt
rust_chengxusheji_yuyan_fix1-2025.3.25.1.dist-info/top_level.txt
rust_chengxusheji_yuyan_fix1-2025.3.25.1.dist-info/RECORD
